Workbook

Sheet Premissas
A1: Projeto GPON Rio Tavares — Premissas
A3: Premissa | B3: Valor | C3: Unidade | D3: Observação
A4: Residências potenciais | B4: 2500 | C4: residências | D4: Premissa do cenário
A5: Taxa de adesão prevista | B5: 0.6 | C5: % | D5: 60% dos usuários potenciais
A6: Clientes iniciais previstos | B6: =B4*B5 -> 1500 | C6: clientes | D6: Meta mínima de atendimento
A7: Orçamento máximo | B7: 250000 | C7: R$ | D7: Limite do projeto
A8: Portas GPON OLT | B8: 32 | C8: portas | D8: OLT única no POP Principal
A9: Split total adotado | B9: 64 | C9: clientes/porta | D9: Arquitetura 1:4 x 1:16
A10: Portas por CTO | B10: 16 | C10: portas | D10: CTO 16 portas
A11: Margem técnica de cabos | B11: 0.15 | C11: % | D11: Reserva para folgas/rotas
A12: Comprimento P1-SD1 | B12: 1262.47 | C12: m | D12: Medido no Google Earth
A13: Comprimento P1-SD2 | B13: 1451.78 | C13: m | D13: Medido no Google Earth
A14: Comprimento SD2-SD3 | B14: 2846.97 | C14: m | D14: Medido no Google Earth

Sheet Dimensionamento
A1: Dimensionamento por Área de Cobertura
A3: Área | B3: Localidade | C3: % da base | D3: Clientes previstos | E3: Portas GPON | F3: CTOs 16p | G3: Split primário 1:4 | H3: Observação
A4: SD1 | B4: Pico da Cruz | C4: 0.15 | D4: =Premissas!$B$6*C4 -> 225 | E4: =ROUNDUP(D4/Premissas!$B$9,0) -> 4 | F4: =ROUNDUP(D4/Premissas!$B$10,0) -> 15 | G4: =E4 -> 4 | H4: Área menor, baixa/média densidade
A5: SD2 | B5: Novo Campeche | C5: 0.35 | D5: =Premissas!$B$6*C5 -> 525 | E5: =ROUNDUP(D5/Premissas!$B$9,0) -> 9 | F5: =ROUNDUP(D5/Premissas!$B$10,0) -> 33 | G5: =E5 -> 9 | H5: Área intermediária
A6: SD3 | B6: Campeche | C6: 0.5 | D6: =Premissas!$B$6*C6 -> 750 | E6: =ROUNDUP(D6/Premissas!$B$9,0) -> 12 | F6: =ROUNDUP(D6/Premissas!$B$10,0) -> 47 | G6: =E6 -> 12 | H6: Maior área e maior concentração
A7: TOTAL | C7: =SUM(C4:C6) -> 1 | D7: =SUM(D4:D6) -> 1500 | E7: =SUM(E4:E6) -> 25 | F7: =SUM(F4:F6) -> 95 | G7: =SUM(G4:G6) -> 25

Sheet Materiais
A1: Planilha de Materiais e Custos — Infraestrutura Inicial
A3: Categoria | B3: Item | C3: Unid. | D3: Qtd. | E3: Valor unit. (R$) | F3: Subtotal (R$) | G3: Critério de cálculo | H3: Área | I3: Incluir? | J3: Observação
A4: POP | B4: OLT Huawei MA5800 equipada 32 portas GPON | C4: un | D4: 1 | E4: 45000 | F4: =D4*E4 -> 45000 | G4: 1 OLT central no POP | H4: POP | I4: Sim | J4: Valor estimado para projeto acadêmico
A5: POP | B5: DIO principal 144 fibras | C5: un | D5: 1 | E5: 2500 | F5: =D5*E5 -> 2500 | G5: DIO no POP Principal | H5: POP | I5: Sim
A6: POP | B6: Rack 44U + nobreak/sistema de energia | C6: un | D6: 1 | E6: 8000 | F6: =D6*E6 -> 8000 | G6: Infraestrutura de central | H6: POP | I6: Sim
A7: POP | B7: Módulo/SFP GPON | C7: un | D7: 32 | E7: 300 | F7: =D7*E7 -> 9600 | G7: 1 por porta GPON da OLT | H7: POP | I7: Sim
A8: Feeder | B8: Cabo óptico 24F P1-SD1 | C8: m | D8: =ROUNDUP(Premissas!B12*(1+Premissas!B11),0) -> 1452 | E8: 3.2 | F8: =D8*E8 -> 4646.4 | G8: Distância Google Earth + 15% | H8: SD1 | I8: Sim
A9: Feeder | B9: Cabo óptico 48F P1-SD2 | C9: m | D9: =ROUNDUP(Premissas!B13*(1+Premissas!B11),0) -> 1670 | E9: 5.5 | F9: =D9*E9 -> 9185 | G9: Distância Google Earth + 15% | H9: SD2 | I9: Sim
A10: Feeder | B10: Cabo óptico 72F SD2-SD3 | C10: m | D10: =ROUNDUP(Premissas!B14*(1+Premissas!B11),0) -> 3275 | E10: 8.5 | F10: =D10*E10 -> 27837.5 | G10: Distância Google Earth + 15% | H10: SD3 | I10: Sim
A11: Distribuição | B11: Cabo óptico 12F distribuição | C11: m | D11: 15000 | E11: 2.2 | F11: =D11*E11 -> 33000 | G11: Estimativa por rotas internas | H11: Todos | I11: Sim | J11: Ajustável após detalhar ruas
A12: Splitter | B12: Splitter primário 1:4 | C12: un | D12: =Dimensionamento!G7 -> 25 | E12: 80 | F12: =D12*E12 -> 2000 | G12: 1 por porta GPON ativa | H12: Todos | I12: Sim | J12: Final 1:64 com CTO 1:16
A13: Splitter | B13: Splitter secundário 1:16 em CTO | C13: un | D13: =Dimensionamento!F7 -> 95 | E13: 120 | F13: =D13*E13 -> 11400 | G13: 1 por CTO | H13: Todos | I13: Sim
A14: CTO | B14: CTO 16 portas | C14: un | D14: =Dimensionamento!F7 -> 95 | E14: 150 | F14: =D14*E14 -> 14250 | G14: CTOs dimensionadas | H14: Todos | I14: Sim
A15: Caixas | B15: Caixa de emenda óptica | C15: un | D15: 12 | E15: 400 | F15: =D15*E15 -> 4800 | G15: Pontos de derivação/rota | H15: Todos | I15: Sim
A16: SD | B16: DIO/caixa de distribuição primária SD | C16: un | D16: 3 | E16: 800 | F16: =D16*E16 -> 2400 | G16: SD1, SD2 e SD3 | H16: Todos | I16: Sim
A17: Serviço | B17: Fusões ópticas | C17: un | D17: 600 | E17: 15 | F17: =D17*E17 -> 9000 | G17: Estimativa geral da planta | H17: Todos | I17: Sim
A18: Acessórios | B18: Cordões, conectores e organizadores | C18: lote | D18: 1 | E18: 2500 | F18: =D18*E18 -> 2500 | G18: Lote técnico | H18: Todos | I18: Sim
A19: Infra | B19: Ferragens, abraçadeiras e fixação | C19: un | D19: =Dimensionamento!F7 -> 95 | E19: 80 | F19: =D19*E19 -> 7600 | G19: 1 conjunto por CTO | H19: Todos | I19: Sim
A20: Serviço | B20: Mão de obra implantação rede feeder/distribuição | C20: lote | D20: 1 | E20: 50000 | F20: =D20*E20 -> 50000 | G20: Lançamento, conectorização e testes | H20: Todos | I20: Sim | J20: Estimativa macro
A22: Resumo
A23: Total estimado | B23: =SUM(F4:F20) -> 243718.9
A24: Orçamento máximo | B24: =Premissas!B7 -> 250000
A25: Saldo | B25: =B24-B23 -> 6281.1
A26: Custo por cliente | B26: =B23/Premissas!B6 -> 162.47927

Sheet Link Budget
A1: Cálculo do Enlace Óptico — Link Budget Simplificado
A3: Cenário | B3: Fibra considerada (km) | C3: Perda fibra (dB) | D3: Splitter 1:4 (dB) | E3: Splitter 1:16 (dB) | F3: Perda total com margem (dB)
A4: SD1 - Pico da Cruz | B4: =Premissas!B12/1000+1 -> 2.26247 | C4: =B4*0.35 -> 0.7918645 | D4: =7.2 -> 7.2 | E4: =13.5 -> 13.5 | F4: =C4+D4+E4+1+1+3 -> 26.491864
A5: SD2 - Novo Campeche | B5: =Premissas!B13/1000+1 -> 2.45178 | C5: =B5*0.35 -> 0.858123 | D5: =7.2 -> 7.2 | E5: =13.5 -> 13.5 | F5: =C5+D5+E5+1+1+3 -> 26.558123
A6: SD3 - Campeche | B6: =(Premissas!B13+Premissas!B14)/1000+1 -> 5.29875 | C6: =B6*0.35 -> 1.8545625 | D6: =7.2 -> 7.2 | E6: =13.5 -> 13.5 | F6: =C6+D6+E6+1+1+3 -> 27.554562
A8: Parâmetro | B8: Valor
A9: Potência TX OLT | B9: +3 dBm
A10: Sensibilidade ONU | B10: -27 dBm
A11: Orçamento óptico disponível | B11: 30 dB
A12: Margem adicional considerada | B12: 3 dB
A13: Conclusão | B13: Verificar se perda total <= 30 dB

Sheet Resumo
A1: Resumo Executivo — Projeto GPON Rio Tavares
A3: Indicador | B3: Valor
A4: Clientes previstos | B4: =Premissas!B6 -> 1500
A5: Portas GPON ativas | B5: =Dimensionamento!E7 -> 25
A6: Portas GPON disponíveis | B6: =Premissas!B8 -> 32
A7: Portas reserva | B7: =B6-B5 -> 7
A8: CTOs previstas | B8: =Dimensionamento!F7 -> 95
A9: Splitters primários 1:4 | B9: =Dimensionamento!G7 -> 25
A10: Splitters secundários 1:16 | B10: =Dimensionamento!F7 -> 95
A11: Custo total estimado | B11: =Materiais!B23 -> 243718.9
A13: Área | B13: Clientes | C13: Portas GPON | D13: CTOs | E13: % base | F13: Observação
A14: =Dimensionamento!A4 -> SD1 | B14: =Dimensionamento!D4 -> 225 | C14: =Dimensionamento!E4 -> 4 | D14: =Dimensionamento!F4 -> 15 | E14: =Dimensionamento!C4 -> 0.15 | F14: =Dimensionamento!H4 -> Área menor, baixa/média densidade
A15: =Dimensionamento!A5 -> SD2 | B15: =Dimensionamento!D5 -> 525 | C15: =Dimensionamento!E5 -> 9 | D15: =Dimensionamento!F5 -> 33 | E15: =Dimensionamento!C5 -> 0.35 | F15: =Dimensionamento!H5 -> Área intermediária
A16: =Dimensionamento!A6 -> SD3 | B16: =Dimensionamento!D6 -> 750 | C16: =Dimensionamento!E6 -> 12 | D16: =Dimensionamento!F6 -> 47 | E16: =Dimensionamento!C6 -> 0.5 | F16: =Dimensionamento!H6 -> Maior área e maior concentração
